yamlpack/__init__.py
yamlpack/__main__.py
yamlpack/make_pack.py
yamlpack/cli/__init__.py
yamlpack/cli/actions.py
yamlpack/cli/parser.py
yamlpack/local/__init__.py
yamlpack/local/builder_cls.py
yamlpack/local/builders.py
yamlpack/local/settings.py
yamlpack/local/user_data.py
yamlpack/local/util.py
yamlpack/resources/__init__.py
yamlpack-0.3.0.dist-info/licenses/LICENSE
yamlpack-0.3.0.dist-info/METADATA
yamlpack-0.3.0.dist-info/WHEEL
yamlpack-0.3.0.dist-info/entry_points.txt
yamlpack-0.3.0.dist-info/top_level.txt
yamlpack-0.3.0.dist-info/RECORD
