Metadata-Version: 2.4
Name: yamlpack
Version: 0.3.0
Summary: Package boilerplate creator using YAML schemas
Home-page: https://github.com/clntsf/yamlpack
Author: Colin Simon-Fellowes
Author-email: colin.tsf@gmail.com
Project-URL: Repo, https://github.com/clntsf/yamlpack
Classifier: Programming Language :: Python :: 3
Classifier: License :: OSI Approved :: MIT License
Requires-Python: >=3.12.2
License-File: LICENSE
Requires-Dist: pyyaml>=6.0.0
Requires-Dist: platformdirs>=4.3.0
Dynamic: author
Dynamic: author-email
Dynamic: classifier
Dynamic: description
Dynamic: description-content-type
Dynamic: home-page
Dynamic: license-file
Dynamic: project-url
Dynamic: requires-dist
Dynamic: requires-python
Dynamic: summary
